LK_Info_Flow/__init__.py
LK_Info_Flow/causality_subspace.py
LK_Info_Flow/multi_causality_est.py
LK_Info_Flow/plot_causality.py
LK_Info_Flow/utils.py
LK_Info_Flow/examples/case1_bivariate_causality.py
LK_Info_Flow/examples/case2_multivariate_causality_and_causal_graph.py
LK_Info_Flow/examples/case3_panel_data_causality.py
LK_Info_Flow/examples/case4_subsystems.py
LK_Info_Flow/examples/case5_takens_theorem.py
LK_Info_Flow/examples/case6_computing cost.py
LK_Info_Flow/examples/case7_cross_correlated_noise.py
LK_Info_Flow/examples/case8_time varying.py
LK_Info_Flow-3.1.2.1.dist-info/METADATA
LK_Info_Flow-3.1.2.1.dist-info/WHEEL
LK_Info_Flow-3.1.2.1.dist-info/top_level.txt
LK_Info_Flow-3.1.2.1.dist-info/RECORD
