Metadata-Version: 2.1
Name: LK_Info_Flow
Version: 3.1.2.1
Summary: Liang Information Flow Package
Author-email: Yineng Rong <yinengrong@foxmail.com>, "X. San Liang" <xsanliang@fudan.edu.cn>
Maintainer-email: Yineng Rong <yinengrong@foxmail.com>
Classifier: Programming Language :: Python :: 3
Classifier: License :: OSI Approved :: MIT License
Classifier: Operating System :: OS Independent
Requires-Dist: numpy
Requires-Dist: scipy
Requires-Dist: graphviz
